sketch_nn/__init__.py
sketch_nn/designer.py
sketch_nn/utils.py
sketch_nn-0.1.7.dist-info/LICENSE
sketch_nn-0.1.7.dist-info/METADATA
sketch_nn-0.1.7.dist-info/WHEEL
sketch_nn-0.1.7.dist-info/top_level.txt
sketch_nn-0.1.7.dist-info/RECORD
