Metadata-Version: 2.1
Name: sketch-nn
Version: 0.1.7
Summary: A tool to generate PyTorch neural network code from flowchart images
Home-page: https://github.com/arcAman07/sketch_nn
Author: Aman Sharma
Author-email: amananytime07@gmail.com
Classifier: Programming Language :: Python :: 3
Classifier: License :: OSI Approved :: MIT License
Classifier: Operating System :: OS Independent
Requires-Python: >=3.6
License-File: LICENSE
Requires-Dist: opencv-python
Requires-Dist: numpy
Requires-Dist: pytesseract
Requires-Dist: torch
Requires-Dist: gradio
Requires-Dist: fastapi
Requires-Dist: uvicorn
